<?xml version="1.0" encoding="UTF-8"?>
<!DOCTYPE tiles-definitions PUBLIC "-//Apache Software Foundation//DTD Tiles Configuration 3.0//EN"
         "http://tiles.apache.org/dtds/tiles-config_3_0.dtd">

<tiles-definitions>
    <definition name="baseLayout" template="/WEB-INF/layout/user/userbase.jsp">
        <put-attribute name="title" value="..." />
        <put-attribute name="header" value="/WEB-INF/layout/user/userheader.jsp" />
        <put-attribute name="footer" value="/WEB-INF/layout/user/userfooter.jsp" />
        <put-attribute name="content" value="..." />
    </definition>
    <definition name="index" extends="baseLayout">
        <put-attribute name="title" value="Trang chủ" />
        <put-attribute name="content" value="/WEB-INF/jsp/index.jsp" />
    </definition>
    <definition name="login" extends="baseLayout">
        <put-attribute name="title" value="Đăng nhập" />
        <put-attribute name="content" value="/WEB-INF/jsp/login.jsp" />
    </definition>
    <definition name="register" extends="baseLayout">
        <put-attribute name="title" value="Đăng ký" />
        <put-attribute name="content" value="/WEB-INF/jsp/register.jsp" />
    </definition>
    <definition name="products" extends="baseLayout">
        <put-attribute name="title" value="Danh sách sản phẩm" />
        <put-attribute name="content" value="/WEB-INF/jsp/products.jsp" />
    </definition>
    <definition name="detail" extends="baseLayout">
        <put-attribute name="title" value="Chi tiết" />
        <put-attribute name="content" value="/WEB-INF/jsp/product-detail.jsp" />
    </definition>
    <definition name="cart" extends="baseLayout">
        <put-attribute name="title" value="Giỏ hàng" />
        <put-attribute name="content" value="/WEB-INF/jsp/cart.jsp" />
    </definition>
    <definition name="history" extends="baseLayout">
        <put-attribute name="title" value="lich su" />
        <put-attribute name="content" value="/WEB-INF/jsp/shopping-history.jsp" />
    </definition>
    <definition name="baseSellerLayout" template="/WEB-INF/layout/seller/adminbase.jsp">
        <put-attribute name="title" value="..." />
        <put-attribute name="header" value="/WEB-INF/layout/seller/adminheader.jsp" />
        <put-attribute name="nav" value="/WEB-INF/layout/seller/adminnav.jsp" />
        <put-attribute name="footer" value="/WEB-INF/layout/seller/adminfooter.jsp" />
        <put-attribute name="content" value="..." />
    </definition>
    <definition name="add-product" extends="baseSellerLayout">
        <put-attribute name="title" value="Thêm sản phẩm" />
        <put-attribute name="content" value="/WEB-INF/jsp/add-product.jsp" />
    </definition>
    <definition name="seller-home" extends="baseSellerLayout">
        <put-attribute name="title" value="Quản lý sản phẩm" />
        <put-attribute name="content" value="/WEB-INF/jsp/seller-home.jsp" />
    </definition>
    <definition name="listProducts" extends="baseSellerLayout">
        <put-attribute name="title" value="Danh sách sản phẩm" />
        <put-attribute name="content" value="/WEB-INF/jsp/list-products.jsp" />
    </definition>
    <definition name="sellerComment" extends="baseSellerLayout">
        <put-attribute name="title" value="Danh sách cmt" />
        <put-attribute name="content" value="/WEB-INF/jsp/seller-cmt.jsp" />
    </definition>
    <definition name="seller-detail" extends="baseSellerLayout">
        <put-attribute name="title" value="Chỉnh sửa sản phẩm" />
        <put-attribute name="content" value="/WEB-INF/jsp/seller-product-detail.jsp" />
    </definition>
    <definition name="baseAdminLayout" template="/WEB-INF/layout/adminpage/adminpagebase.jsp">
        <put-attribute name="title" value="..." />
        <put-attribute name="header" value="/WEB-INF/layout/adminpage/adminpageheader.jsp" />
        <put-attribute name="nav" value="/WEB-INF/layout/adminpage/adminpagenav.jsp" />
        <put-attribute name="btn" value="/WEB-INF/layout/adminpage/adminpagesettingbtn.jsp" />
        <put-attribute name="footer" value="/WEB-INF/layout/adminpage/adminpagefooter.jsp" />
        <put-attribute name="content" value="..." />
    </definition>
    <definition name="admin" extends="baseAdminLayout">
        <put-attribute name="title" value="admin" />
        <put-attribute name="content" value="/WEB-INF/jsp/admin.jsp" />
    </definition>
    <definition name="stats" extends="baseAdminLayout">
        <put-attribute name="title" value="stats" />
        <put-attribute name="content" value="/WEB-INF/jsp/statbyseller.jsp" />
    </definition>
    <definition name="error404" extends="baseAdminLayout">
        <put-attribute name="title" value="stats" />
        <put-attribute name="content" value="/WEB-INF/jsp/404page.jsp" />
    </definition>
</tiles-definitions>

